<?xml version="1.0" encoding="utf-8"?>
<catalog>
  <remote>2017.1-dev</remote>
  <support_commit_id>f2f2c8d9db8b7129479347fb60ba01e3a8243721</support_commit_id>
  <release>2017.1</release>
  <revision>2.4</revision>
  <app_display_order>ultrafast,debugutils,designutils,projutils,incrcompile,xsim,modelsim,questa,ies,vcs,riviera,activehdl,spyglass,protoip,pcbutils,diff,profiler,junit,tk_tunnel</app_display_order>
  <apps>
    <app>
      <name>activehdl</name>
      <company>aldec</company>
      <commit_id>a302298cd95e7d1598340b511b8e97e03ed6e245</commit_id>
      <revision>1.8</revision>
    </app>
    <app>
      <name>debugutils</name>
      <company>xilinx</company>
      <commit_id>a302298cd95e7d1598340b511b8e97e03ed6e245</commit_id>
      <revision>1.1</revision>
    </app>
    <app>
      <name>designutils</name>
      <company>xilinx</company>
      <commit_id>a302298cd95e7d1598340b511b8e97e03ed6e245</commit_id>
      <revision>1.29</revision>
    </app>
    <app>
      <name>diff</name>
      <company>xilinx</company>
      <commit_id>a302298cd95e7d1598340b511b8e97e03ed6e245</commit_id>
      <revision>2.3</revision>
    </app>
    <app>
      <name>ies</name>
      <company>xilinx</company>
      <commit_id>9277c0370682a80b6146608517a52720484b3e02</commit_id>
      <revision>3.28</revision>
    </app>
    <app>
      <name>incrcompile</name>
      <company>xilinx</company>
      <commit_id>a302298cd95e7d1598340b511b8e97e03ed6e245</commit_id>
      <revision>1.2</revision>
    </app>
    <app>
      <name>junit</name>
      <company>xilinx</company>
      <commit_id>a302298cd95e7d1598340b511b8e97e03ed6e245</commit_id>
      <revision>1.0</revision>
    </app>
    <app>
      <name>modelsim</name>
      <company>xilinx</company>
      <commit_id>f46074f601de722a184e6c9c08bcd01e471ef455</commit_id>
      <revision>2.137</revision>
    </app>
    <app>
      <name>myapp</name>
      <company>mycompany</company>
      <commit_id>a302298cd95e7d1598340b511b8e97e03ed6e245</commit_id>
      <revision>1.0</revision>
    </app>
    <app>
      <name>myapp6</name>
      <company>mycompany</company>
      <commit_id>a302298cd95e7d1598340b511b8e97e03ed6e245</commit_id>
      <revision>2.15</revision>
    </app>
    <app>
      <name>pcbutils</name>
      <company>xilinx</company>
      <commit_id>a302298cd95e7d1598340b511b8e97e03ed6e245</commit_id>
      <revision>1.2</revision>
    </app>
    <app>
      <name>profiler</name>
      <company>xilinx</company>
      <commit_id>a302298cd95e7d1598340b511b8e97e03ed6e245</commit_id>
      <revision>1.0</revision>
    </app>
    <app>
      <name>projutils</name>
      <company>xilinx</company>
      <commit_id>f90e8ba4a6407f50759df08969a4905d69ff7d25</commit_id>
      <revision>3.213</revision>
    </app>
    <app>
      <name>protoip</name>
      <company>icl</company>
      <commit_id>a302298cd95e7d1598340b511b8e97e03ed6e245</commit_id>
      <revision>2.0</revision>
    </app>
    <app>
      <name>questa</name>
      <company>xilinx</company>
      <commit_id>9277c0370682a80b6146608517a52720484b3e02</commit_id>
      <revision>2.28</revision>
    </app>
    <app>
      <name>riviera</name>
      <company>aldec</company>
      <commit_id>a302298cd95e7d1598340b511b8e97e03ed6e245</commit_id>
      <revision>1.8</revision>
    </app>
    <app>
      <name>spyglass</name>
      <company>atrenta</company>
      <commit_id>a302298cd95e7d1598340b511b8e97e03ed6e245</commit_id>
      <revision>1.5</revision>
    </app>
    <app>
      <name>template</name>
      <company>mycompany</company>
      <commit_id>1633320bfb92cb15f583a0ae725254682cce9ca9</commit_id>
      <revision>1.0</revision>
    </app>
    <app>
      <name>tk_tunnel</name>
      <company>xilinx</company>
      <commit_id>a302298cd95e7d1598340b511b8e97e03ed6e245</commit_id>
      <revision>1.7</revision>
    </app>
    <app>
      <name>ultrafast</name>
      <company>xilinx</company>
      <commit_id>a302298cd95e7d1598340b511b8e97e03ed6e245</commit_id>
      <revision>1.7</revision>
    </app>
    <app>
      <name>vcs</name>
      <company>xilinx</company>
      <commit_id>9277c0370682a80b6146608517a52720484b3e02</commit_id>
      <revision>3.32</revision>
    </app>
    <app>
      <name>xsim</name>
      <company>xilinx</company>
      <commit_id>bfc6588b73262d70282d56f7858ad0a8250faf39</commit_id>
      <revision>2.142</revision>
    </app>
  </apps>
</catalog>
